mlax/__init__.py
mlax/_test_utils.py
mlax/_utils.py
mlax/module.py
mlax/nn/__init__.py
mlax/nn/bias.py
mlax/nn/conv.py
mlax/nn/embed.py
mlax/nn/f.py
mlax/nn/functional.py
mlax/nn/linear.py
mlax/nn/parallel.py
mlax/nn/recurrent.py
mlax/nn/scaler.py
mlax/nn/series.py
mlax/nn/z_norm.py
mlax_nn-0.2.6.dist-info/LICENSE
mlax_nn-0.2.6.dist-info/METADATA
mlax_nn-0.2.6.dist-info/WHEEL
mlax_nn-0.2.6.dist-info/top_level.txt
mlax_nn-0.2.6.dist-info/RECORD
