Metadata-Version: 2.1
Name: mlax-nn
Version: 0.2.6
Summary: A pure functional machine learning library build on top of Google JAX.
Home-page: https://github.com/zongyf02/mlax
Author: Yifan Zong
Author-email: y22zong@uwaterloo.ca
Classifier: Programming Language :: Python :: 3.8
Classifier: Programming Language :: Python :: 3.9
Classifier: Programming Language :: Python :: 3.10
Classifier: License :: OSI Approved :: MIT License
Classifier: Topic :: Scientific/Engineering
Classifier: Topic :: Scientific/Engineering :: Mathematics
Classifier: Topic :: Scientific/Engineering :: Artificial Intelligence
Classifier: Topic :: Scientific/Engineering :: Mathematics
Classifier: Topic :: Software Development
Classifier: Topic :: Software Development :: Libraries
Classifier: Topic :: Software Development :: Libraries :: Python Modules
License-File: LICENSE
Requires-Dist: jax (>=0.4.20)
Requires-Dist: jaxlib (>=0.4.20)
Provides-Extra: dev
Requires-Dist: pytest (==7.4.3) ; extra == 'dev'
